builder/__init__.py
builder/__main__.py
candis/__attr__.py
candis/__init__.py
candis/__main__.py
candis/app/__init__.py
candis/app/main.py
candis/app/assets/css/styles.min.css
candis/app/assets/css/vendor/bootstrap-editable.min.css
candis/app/assets/css/vendor/nprogress.min.css
candis/app/assets/css/vendor/toastr.min.css
candis/app/assets/img/logo-title.png
candis/app/assets/img/logo-w-title.png
candis/app/assets/img/logo.png
candis/app/assets/img/icons/clipboard.png
candis/app/assets/img/icons/cloud-computing-o.png
candis/app/assets/img/icons/cloud-computing.png
candis/app/assets/img/icons/column-select.png
candis/app/assets/img/icons/cross-validation.png
candis/app/assets/img/icons/database.png
candis/app/assets/img/icons/delete-column.png
candis/app/assets/img/icons/delete-row.png
candis/app/assets/img/icons/dices.png
candis/app/assets/img/icons/document.png
candis/app/assets/img/icons/documentation.png
candis/app/assets/img/icons/edit.png
candis/app/assets/img/icons/envelope-open.png
candis/app/assets/img/icons/fast-forward-o.png
candis/app/assets/img/icons/floppy-disk.png
candis/app/assets/img/icons/gears.png
candis/app/assets/img/icons/info.png
candis/app/assets/img/icons/insert-column.png
candis/app/assets/img/icons/insert-row.png
candis/app/assets/img/icons/load-rows.png
candis/app/assets/img/icons/network.png
candis/app/assets/img/icons/nodes.png
candis/app/assets/img/icons/pause-o.png
candis/app/assets/img/icons/photo-camera.png
candis/app/assets/img/icons/pie-chart.png
candis/app/assets/img/icons/play-o.png
candis/app/assets/img/icons/quit.png
candis/app/assets/img/icons/reload.png
candis/app/assets/img/icons/rewind-o.png
candis/app/assets/img/icons/settings.png
candis/app/assets/img/icons/stop-o.png
candis/app/assets/img/icons/tree-structure.png
candis/app/assets/img/icons/vector.png
candis/app/assets/js/bundle.min.js
candis/app/assets/js/vendor/MathJax.js
candis/app/assets/js/vendor/bootbox.min.js
candis-0.0.5.dist-info/DESCRIPTION.rst
candis-0.0.5.dist-info/METADATA
candis-0.0.5.dist-info/RECORD
candis-0.0.5.dist-info/WHEEL
candis-0.0.5.dist-info/entry_points.txt
candis-0.0.5.dist-info/metadata.json
candis-0.0.5.dist-info/top_level.txt
