Metadata-Version: 2.0
Name: candis
Version: 0.0.5
Summary: A data mining suite for DNA Microarrays.
Home-page: https://candis.readthedocs.io
Author: Achilles Rasquinha
Author-email: achillesrasquinha@gmail.com
License: MIT
Keywords: data,mining,suite,dna,microarray,bioinformatics
Platform: UNKNOWN
Requires-Dist: addict
Requires-Dist: PyYAML
Requires-Dist: requests
Requires-Dist: numpy
Requires-Dist: scipy
Requires-Dist: matplotlib
Requires-Dist: pandas
Requires-Dist: seaborn
Requires-Dist: rpy2
Requires-Dist: liac-arff
Requires-Dist: Cython
Requires-Dist: javabridge
Requires-Dist: python-weka-wrapper3
Requires-Dist: pygraphviz
Requires-Dist: Pillow
Requires-Dist: Flask
Requires-Dist: django-htmlmin
Requires-Dist: Flask-SocketIO
Requires-Dist: gunicorn
